xcat_mesh/__init__.py
xcat_mesh/cli.py
xcat_mesh/config.py
xcat_mesh/errors.py
xcat_mesh/io.py
xcat_mesh/mesh.py
xcat_mesh/pipeline.py
xcat_mesh/resample.py
xcat_mesh/smooth.py
xcat_mesh/validate.py
xcat_mesh-0.1.1.dist-info/licenses/LICENSE
xcat_mesh-0.1.1.dist-info/METADATA
xcat_mesh-0.1.1.dist-info/WHEEL
xcat_mesh-0.1.1.dist-info/entry_points.txt
xcat_mesh-0.1.1.dist-info/top_level.txt
xcat_mesh-0.1.1.dist-info/RECORD
