Metadata-Version: 2.4
Name: xcat-mesh
Version: 0.1.1
Summary: Convert binary NIfTI segmentation masks to surface meshes (OBJ) with optional GPU Laplacian smoothing.
Author-email: Lavsen Dahal <lavsen.dahal@gmail.com>
License: Apache-2.0
Keywords: xcat,nifti,mesh,marching-cubes,medical-imaging
Requires-Python: >=3.9
License-File: LICENSE
Requires-Dist: numpy>=1.22
Requires-Dist: nibabel>=5.0
Requires-Dist: scikit-image>=0.20
Requires-Dist: scipy>=1.9
Requires-Dist: tqdm>=4.65
Provides-Extra: gpu
Requires-Dist: torch>=2.0; extra == "gpu"
Dynamic: license-file
